{ 
"Restaurants":{
    "El_Cojimero":{
        "Province": "La Habana",
        "Municipality": "La Habana del Este",
        "Location": "5P92+3R7, La Habana",
        "Stars":{
            "Social network": "Google",
            "url": "https://g.co/kgs/GU4Wx7y",
            "total": 4.2,
            "date": "20250108"
        },
        "schedules": "Apertura 12:00m y 10:00pm",
        "Days of the week": "Miercoles a Domingo",
        "Type of food or specialty": "Mariscos",
        "Most popular food": "Pescado",
        "Facilities": {
                "Pets": false,
                "Wheelchair ramp": true,
                "infant stool": true,
                "Smoking area": true,
                "Parking": true,
                "Home service": false,
                "Payment type": "Transferencia y Efectivo"
        },
        "Capacity": 70,
        "menu and prices": {
            "Starters": {
                "Croquetas del Dia": "310",
                "Empanaditas Rellenas": "300",
                "Ensalada de Pollo": "390",
                "Frituras de Malanga": "300",
                "Tostones Rellenos": "400",
                "Tostones Rellenos de Atun": "500",
                "Ensalada de Atun": "530",
                "Eperlan": "420",
                "Ensalada de Pulpo": "700",
                "Ceviche Casero": "550",
                "Coctel de Camaron": "560",
                "Fajitas de Cerdo Empanadas": "420",
                "Fajitas de Pollo Empanadas": "420",
                "Tamal en Cazuela": "600",
                "Coctel de Langosta": "700"
            },
            "Main Dishes": {
                "Bistec de Cerdo a la Pi単a": "1600",
                "Bistec Uruguayo": "1800",
                "Lomo de Cerdo a la Francesa": "1860",
                "Chilindron de Cordero": "1640",
                "Ropa Vieja": "1600",
                "Vaca Frita": "1650",
                "Higado a la Italiana": "1500",
                "Bistec de Higado": "1500",
                "Pechuga de Pollo Grille": "1400",
                "Pechuga de Pollo al Pimiento": "1470",
                "Pechuga de Pollo al Queso": "1700",
                "Pechuga de Pollo Hawaiano": "1780",
                "Cordon Bleu": "1750",
                "Lomo de Cerdo Relleno": "1990",
                "Costilla de Cerdo al Horno": "1800",
                "Carne de Res con Papas": "2200",
                "Conejo Estofado": "2000",
                "Bistec de Res Encebollado": "1960",
                "Filete de Cerdo a la Miel-Mostaza": "2500",
                "Bistec de Res en Cazuela": "1960",
                "Filete de Pescado Grille": "1700",
                "Filete de Pescado Montado": "2100",
                "Filete de Pescado Canciller": "2200",
                "Filete de Pescado Monte Toro": "1990",
                "Filete de Pescado Gratinado": "1990",
                "Filete de Pescado Sote Capricho": "1800",
                "Filete de Pescado al Olivo": "1800",
                "Pargo Asado": "2000",
                "Camarones Grille": "1720",
                "Camarones Enchilados": "1990",
                "Camarones al Ajillo": "1990",
                "Camarones Empanados": "1850",
                "Camarones Grille con Champi単ones": "1990",
                "Enchilado de Pulpo": "2300",
                "Pulpo Grille": "2150",
                "Pulpo al Ajillo": "2150",
                "Filete de Pescado Montado con Langosta": "2500" 
            },
            "Desserts": null,
            "Drinks": {
                "Agua Natural 500ml": "110",
                "Agua Natural 1.5lts": "300",
                "Agua Gaseada Nacional": "120",
                "Agua Tonica Nacional": "150",
                "Agua Tonica Importada": "250",
                "Refrescos Nacionales": "260",
                "Refrescos Importados": "260",
                "Malta": "290",
                "Jugos en Conserva": "220",
                "Jugos El Cojimero": "100",
                "Yogurt Saborizado": "210",
                "Energizantes": "270",
                "Energizante Tigon": "290",
                "Cerveza Nacional": "300",
                "Cerveza Importada": "260",
                "Cheladas Nacionales": "350",
                "Cheladas Importadas": "260",
                "Micheladas Nacionales": "500",
                "Micheladas Importadas": "450",
                "Limonada Natural": "300"
            }, 
            "Cocktails": {
                "Caipiri単a": "450",
                "Mojito": "450",
                "Ron Collins": "450",
                "Cubata": "450",
                "Cuba Libre": "450",
                "Cubanito": "450",
                "Daiquiri Frappe": "500",
                "Daiquiri Blue": "500",
                "Daiquiri Rebelde": "500",
                "Pi単a Colada": "650",
                "Bello Monte": "600",
                "Copa de Vino de la Casa": "500",
                "Alexander": "650",
                "Caipiroska": "650",
                "Caipiroska Absolut": "850",
                "Boody Mary": "650",
                "Blue Lagoon": "650",
                "Sangria": "650",
                "Calimocho": "650",
                "Screwdriver": "650",
                "Screwdriver Absolut": "850",
                "Dry Martini": "900",
                "Margarita": "700",
                "Gin Tonic": "800",
                "Gin Tonic Premium": "1300",
                "Aquamenti": "800",
                "Daiquiri Mulata": "800",
                "Merlina": "800",
                "Purple Gin": "800",
                "Sex on the Beach": "800",
                "Rosita": "800",
                "Sahara": "800",
                "Blue Michelada": "800",
                "Malefica": "800",
                "Queen Charlotte": "800",
                "Devil's Margarita": "800"
            },
            "Coffee": {
                "Espresso": "100",
                "Cortado": "150",
                "Bombon": "190",
                "Americano": "100",
                "Cappuchino": "250"
            }
        }
    }
}
}